Metadata-Version: 2.1
Name: vclibpy
Version: 0.1.2
Summary: Package with functions for the vapor compression process design using steady state simulation models
Home-page: https://github.com/RWTH-EBC/vclibpy
Download-URL: https://github.com/RWTH-EBC/vclibpy/archive/refs/tags/0.1.2.tar.gz
Author: RWTH Aachen University, E.ON Energy Research Center, Institute of Energy Efficient Buildings and Indoor Climate
Author-email: fabian.wuellhorst@eonerc.rwth-aachen.de
License: BSD 3-Clause
Keywords: vapor-compression,heat pumps,chillers,steady-state simulation
Classifier: Development Status :: 3 - Alpha
Classifier: Programming Language :: Python :: 3.8
Classifier: Programming Language :: Python :: 3.9
Classifier: Programming Language :: Python :: 3.10
Classifier: Programming Language :: Python :: 3.11
License-File: LICENSE
Requires-Dist: numpy
Requires-Dist: coolprop
Requires-Dist: matplotlib
Requires-Dist: pandas
Requires-Dist: sdf
Requires-Dist: ctREFPROP
